lismr_delo_js/__init__.py
lismr_delo_js/test.py
lismr_delo_js-0.0.1.dist-info/METADATA
lismr_delo_js-0.0.1.dist-info/WHEEL
lismr_delo_js-0.0.1.dist-info/top_level.txt
lismr_delo_js-0.0.1.dist-info/RECORD
