Metadata-Version: 2.4
Name: lismr-delo-js
Version: 0.0.1
Summary: Test package for PyPI publishing
Author: lismrdelo
Requires-Python: >=3.8
